netmeasure/__init__.py
netmeasure/__main__.py
netmeasure/cli.py
netmeasure/measurements/__init__.py
netmeasure/measurements/base/__init__.py
netmeasure/measurements/base/measurements.py
netmeasure/measurements/base/results.py
netmeasure/measurements/file_download/__init__.py
netmeasure/measurements/file_download/measurements.py
netmeasure/measurements/file_download/results.py
netmeasure/measurements/file_download/tests/__init__.py
netmeasure/measurements/file_download/tests/test_measurements.py
netmeasure/measurements/ip_route/measurements.py
netmeasure/measurements/ip_route/results.py
netmeasure/measurements/ip_route/tests/__init__.py
netmeasure/measurements/ip_route/tests/test_measurements.py
netmeasure/measurements/latency/__init__.py
netmeasure/measurements/latency/measurements.py
netmeasure/measurements/latency/results.py
netmeasure/measurements/latency/tests/__init__.py
netmeasure/measurements/latency/tests/test_measurements.py
netmeasure/measurements/netflix_fast/__init__.py
netmeasure/measurements/netflix_fast/measurements.py
netmeasure/measurements/netflix_fast/results.py
netmeasure/measurements/netflix_fast/tests/__init__.py
netmeasure/measurements/netflix_fast/tests/test_measurements.py
netmeasure/measurements/speedtest_dotnet/__init__.py
netmeasure/measurements/speedtest_dotnet/measurements.py
netmeasure/measurements/speedtest_dotnet/results.py
netmeasure/measurements/speedtest_dotnet/tests/__init__.py
netmeasure/measurements/speedtest_dotnet/tests/test_measurements.py
netmeasure/measurements/webpage_download/__init__.py
netmeasure/measurements/webpage_download/measurements.py
netmeasure/measurements/webpage_download/results.py
netmeasure/measurements/webpage_download/tests/__init__.py
netmeasure/measurements/webpage_download/tests/test_measurements.py
netmeasure/measurements/youtube_download/__init__.py
netmeasure/measurements/youtube_download/measurements.py
netmeasure/measurements/youtube_download/results.py
netmeasure-1.4.0.dist-info/LICENSE.txt
netmeasure-1.4.0.dist-info/METADATA
netmeasure-1.4.0.dist-info/WHEEL
netmeasure-1.4.0.dist-info/entry_points.txt
netmeasure-1.4.0.dist-info/RECORD
