Metadata-Version: 2.1
Name: netmeasure
Version: 1.4.0
Summary: Measure Internet connection quality.
Home-page: https://github.com/amorphitec/netmeasure
Author: James Stewart
Author-email: james@amorphitec.io
Maintainer: James Stewart
Maintainer-email: james@amorphitec.io
Requires-Python: >=3.8,<4
Classifier: Programming Language :: Python :: 3
Classifier: Programming Language :: Python :: 3.8
Classifier: Programming Language :: Python :: 3.9
Classifier: Programming Language :: Python :: 3.10
Classifier: Programming Language :: Python :: 3.11
Requires-Dist: beautifulsoup4 (>=4.11.2,<5.0.0)
Requires-Dist: click (>=8.1.3,<9.0.0)
Requires-Dist: exitstatus (>=2.3.0,<3.0.0)
Requires-Dist: halo (>=0.0.31,<0.0.32)
Requires-Dist: requests (>=2.28,<3.0)
Requires-Dist: rich (>=13.3.2,<14.0.0)
Requires-Dist: scapy (>=2.5,<3.0)
Requires-Dist: speedtest-cli (>=2.1,<3.0)
Requires-Dist: validators (>=0.20,<0.21)
Requires-Dist: yt-dlp (>=2023.9.24,<2024.0.0)
Project-URL: Repository, https://github.com/amorphitec/netmeasure
